nestipy_peewee/__init__.py
nestipy_peewee/peewee_builder.py
nestipy_peewee/peewee_decorator.py
nestipy_peewee/peewee_meta.py
nestipy_peewee/peewee_module.py
nestipy_peewee-0.2.4.dist-info/LICENSE
nestipy_peewee-0.2.4.dist-info/METADATA
nestipy_peewee-0.2.4.dist-info/WHEEL
nestipy_peewee-0.2.4.dist-info/RECORD
